gitsup/__init__.py
gitsup/_version.py
gitsup/config.py
gitsup/main.py
gitsup/update.py
gitsup-0.7.0.dist-info/LICENSE
gitsup-0.7.0.dist-info/METADATA
gitsup-0.7.0.dist-info/WHEEL
gitsup-0.7.0.dist-info/entry_points.txt
gitsup-0.7.0.dist-info/top_level.txt
gitsup-0.7.0.dist-info/zip-safe
gitsup-0.7.0.dist-info/RECORD
